easings/__init__.py
easings/consts.py
easings/easings.py
easings/curves/__init__.py
easings/curves/bezier.py
easings/splines/__init__.py
easings/splines/b_spline.py
easings/splines/bezier.py
easings/splines/catmull.py
easings-4.1.2.dist-info/METADATA
easings-4.1.2.dist-info/WHEEL
easings-4.1.2.dist-info/top_level.txt
easings-4.1.2.dist-info/RECORD
